LICENSE.txt
MANIFEST.in
Makefile
README.md
pytest.ini
setup.cfg
setup.py
test_viaenv.py
viaenv.py
viaenv.egg-info/PKG-INFO
viaenv.egg-info/SOURCES.txt
viaenv.egg-info/dependency_links.txt
viaenv.egg-info/top_level.txt